promptquality/__init__.py
promptquality/callback.py
promptquality/chain_run_module.py
promptquality/constants/__init__.py
promptquality/constants/config.py
promptquality/constants/dataset_format.py
promptquality/constants/job.py
promptquality/constants/models.py
promptquality/constants/prompt_optimization.py
promptquality/constants/routes.py
promptquality/constants/row.py
promptquality/constants/run.py
promptquality/constants/scorers.py
promptquality/core_helpers/__init__.py
promptquality/core_helpers/api_key.py
promptquality/core_helpers/dataset.py
promptquality/core_helpers/group.py
promptquality/core_helpers/group_integration.py
promptquality/core_helpers/group_project.py
promptquality/core_helpers/integration.py
promptquality/core_helpers/project.py
promptquality/core_helpers/user.py
promptquality/core_helpers/user_integration.py
promptquality/core_helpers/user_project.py
promptquality/evaluate_samples.py
promptquality/get_metrics_module.py
promptquality/get_rows_module.py
promptquality/get_run_scorer_jobs_module.py
promptquality/get_template_module.py
promptquality/helpers.py
promptquality/integrations.py
promptquality/job_progress_module.py
promptquality/login_module.py
promptquality/prompt_optimization.py
promptquality/py.typed
promptquality/registered_scorers.py
promptquality/run_module.py
promptquality/run_sweep_module.py
promptquality/sweep_module.py
promptquality/types/__init__.py
promptquality/types/chains/__init__.py
promptquality/types/chains/row.py
promptquality/types/config.py
promptquality/types/custom_scorer.py
promptquality/types/customized_scorer.py
promptquality/types/evaluate_samples.py
promptquality/types/pagination.py
promptquality/types/prompt_optimization.py
promptquality/types/registered_scorers.py
promptquality/types/rows.py
promptquality/types/run.py
promptquality/types/settings.py
promptquality/types/user_submitted_metrics.py
promptquality/utils/__init__.py
promptquality/utils/api_client.py
promptquality/utils/dataset.py
promptquality-1.14.0.dist-info/LICENSE
promptquality-1.14.0.dist-info/METADATA
promptquality-1.14.0.dist-info/WHEEL
promptquality-1.14.0.dist-info/RECORD
