Metadata-Version: 2.3
Name: promptquality
Version: 1.14.0
Summary: 🦸 Supercharge your prompts with Galileo Evaluate!
License: Apache-2.0
Keywords: prompt,nlp,llm,quality,language_models,galileo
Author: Galileo Technologies Inc.
Author-email: team@rungalileo.io
Requires-Python: >=3.9
Classifier: Development Status :: 5 - Production/Stable
Classifier: Framework :: Pydantic
Classifier: License :: OSI Approved :: Apache Software License
Classifier: Framework :: IPython
Classifier: Framework :: Jupyter
Classifier: Framework :: Jupyter :: JupyterLab
Classifier: Intended Audience :: Developers
Classifier: Topic :: Scientific/Engineering :: Artificial Intelligence
Provides-Extra: all
Provides-Extra: arrow
Provides-Extra: langchain
Requires-Dist: galileo-core (>=3.62.0,<4.0.0)
Requires-Dist: langchain-community (>=0.3.14,<0.4.0) ; extra == "langchain" or extra == "all"
Requires-Dist: langchain-core (>=0.3.55,<0.4.0) ; extra == "langchain" or extra == "all"
Requires-Dist: pyarrow (>=18,<22) ; extra == "arrow" or extra == "all"
Requires-Dist: pydantic (>=2.11.7,<3.0.0)
Requires-Dist: pydantic-settings (>=2.10.1,<3.0.0)
Requires-Dist: pyjwt (>=2.10.1,<3.0.0)
Requires-Dist: requests (>=2.32.4,<3.0.0)
Requires-Dist: tqdm (>=4.65.0,<5.0.0)
Project-URL: Documentation, https://promptquality.docs.galileo.ai/
Project-URL: Homepage, https://www.galileo.ai/
